setup.py
swiss_chard.egg-info/PKG-INFO
swiss_chard.egg-info/SOURCES.txt
swiss_chard.egg-info/dependency_links.txt
swiss_chard.egg-info/requires.txt
swiss_chard.egg-info/top_level.txt
swisschard/__init__.py
swisschard/scheduler.py
tests/__init__.py
tests/app.py
tests/test_integration.py