Metadata-Version: 1.0
Name: swiss-chard
Version: 1.0.0
Summary: swiss-chard - redis backed scheduler for celery beat.
Home-page: https://github.com/SPSCommerce/swiss-chard
Author: pjdecoursey
Author-email: webapps@spscommerce.com
License: MIT
Platform: UNKNOWN
